Sem3Py/Numerical.py
Sem3Py/Optimization.py
Sem3Py/__init__.py
Sem3Py-0.0.7.dist-info/LICENSE
Sem3Py-0.0.7.dist-info/METADATA
Sem3Py-0.0.7.dist-info/WHEEL
Sem3Py-0.0.7.dist-info/top_level.txt
Sem3Py-0.0.7.dist-info/RECORD
